compy_python/__init__.py
compy_python/configclass.py
compy_python/custom_types.py
compy_python/dict_get.py
compy_python/exceptionclass.py
compy_python/lists.py
compy_python/math.py
compy_python/nones.py
compy_python/ownership.py
compy_python/printing.py
compy_python/resources.py
compy_python/strings.py
compy_python/tuple_get.py
compy_python/union.py
compy_python/stl/__init__.py
compy_python/stl/compy_time.py
compy_python-0.0.6.dist-info/METADATA
compy_python-0.0.6.dist-info/WHEEL
compy_python-0.0.6.dist-info/licenses/LICENSE
compy_python-0.0.6.dist-info/RECORD
