Metadata-Version: 2.4
Name: compy-python
Version: 0.0.6
Summary: contains necessary python code for Compy projects
Project-URL: Homepage, https://github.com/curtispuetz/compy-python
Author-email: Curtis Puetz <compy.main@gmail.com>
License: MIT
License-File: LICENSE
Requires-Python: >=3.13
